p8s/__init__.py
p8s/csrf.py
p8s/messages.py
p8s/middleware.py
p8s/pagination.py
p8s/staticfiles.py
p8s/admin/__init__.py
p8s/admin/actions.py
p8s/admin/export.py
p8s/admin/inlines.py
p8s/admin/logs.py
p8s/admin/registry.py
p8s/admin/router.py
p8s/admin/site.py
p8s/admin/static/index.html
p8s/admin/static/p8s.svg
p8s/admin/static/assets/index-5d9726b3.js
p8s/admin/static/assets/index-75a52ac1.css
p8s/admin/static/assets/p8s-3e4de0f0.svg
p8s/admin/ui/index.html
p8s/admin/ui/package-lock.json
p8s/admin/ui/package.json
p8s/admin/ui/tsconfig.json
p8s/admin/ui/tsconfig.node.json
p8s/admin/ui/vite.config.ts
p8s/admin/ui/public/p8s.svg
p8s/admin/ui/src/main.tsx
p8s/admin/ui/src/vite-env.d.ts
p8s/admin/ui/src/api/admin.ts
p8s/admin/ui/src/assets/p8s.svg
p8s/admin/ui/src/components/admin/AdminPanel.tsx
p8s/admin/ui/src/components/admin/DataTable.tsx
p8s/admin/ui/src/components/admin/DynamicForm.tsx
p8s/admin/ui/src/components/admin/InlineEditor.tsx
p8s/admin/ui/src/components/admin/Sidebar.tsx
p8s/admin/ui/src/components/admin/admin.css
p8s/admin/ui/src/components/admin/index.ts
p8s/admin/ui/src/components/admin/fields/CodeEditor.tsx
p8s/admin/ui/src/components/admin/fields/ColorPickerField.tsx
p8s/admin/ui/src/components/admin/fields/ResizableImage.tsx
p8s/admin/ui/src/components/admin/fields/RichTextEditor.tsx
p8s/admin/ui/src/components/admin/fields/SlashCommandList.tsx
p8s/admin/ui/src/components/admin/fields/TagsInput.tsx
p8s/admin/ui/src/components/admin/fields/index.ts
p8s/admin/ui/src/types/admin.ts
p8s/ai/__init__.py
p8s/ai/client.py
p8s/ai/config.py
p8s/ai/fields.py
p8s/ai/processor.py
p8s/ai/vector_search.py
p8s/auth/__init__.py
p8s/auth/decorators.py
p8s/auth/dependencies.py
p8s/auth/mfa.py
p8s/auth/models.py
p8s/auth/password.py
p8s/auth/permissions.py
p8s/auth/router.py
p8s/auth/security.py
p8s/auth/social/__init__.py
p8s/auth/social/models.py
p8s/auth/social/providers.py
p8s/auth/social/router.py
p8s/cache/__init__.py
p8s/cache/backends.py
p8s-1.5.2.dist-info/METADATA
p8s-1.5.2.dist-info/WHEEL
p8s-1.5.2.dist-info/entry_points.txt
p8s-1.5.2.dist-info/licenses/LICENSE
p8s-1.5.2.dist-info/RECORD
