Metadata-Version: 2.4
Name: p8s
Version: 1.5.2
Summary: A batteries-included async Python framework combining Django's DX with FastAPI's performance
Project-URL: About, https://peppe37.github.io/p8s/about/
Project-URL: Documentation, https://peppe37.github.io/p8s/
Project-URL: Repository, https://github.com/Peppe37/p8s
Author: Giuseppe Lapietra
License-Expression: MIT
License-File: LICENSE
Keywords: ai,async,django,fastapi,framework,fullstack,llm,react
Classifier: Development Status :: 3 - Alpha
Classifier: Framework :: FastAPI
Classifier: Intended Audience :: Developers
Classifier: License :: OSI Approved :: MIT License
Classifier: Programming Language :: Python :: 3
Classifier: Programming Language :: Python :: 3.10
Classifier: Programming Language :: Python :: 3.11
Classifier: Programming Language :: Python :: 3.12
Classifier: Programming Language :: Python :: 3.13
Classifier: Topic :: Internet :: WWW/HTTP :: Dynamic Content
Classifier: Topic :: Internet :: WWW/HTTP :: HTTP Servers
Classifier: Topic :: Internet :: WWW/HTTP :: Site Management
Classifier: Topic :: Software Development :: Libraries :: Application Frameworks
Requires-Python: >=3.10
Requires-Dist: aiofiles>=23.2.0
Requires-Dist: aiosqlite>=0.19.0
Requires-Dist: alembic>=1.13.0
Requires-Dist: asyncpg>=0.29.0
Requires-Dist: email-validator>=2.0.0
Requires-Dist: fastapi>=0.109.0
Requires-Dist: httpx>=0.25.0
Requires-Dist: instructor>=0.5.0
Requires-Dist: litellm>=1.20.0
Requires-Dist: numpy>=1.26.0
Requires-Dist: passlib[bcrypt]>=1.7.4
Requires-Dist: pgvector>=0.2.0
Requires-Dist: pydantic-settings>=2.1.0
Requires-Dist: pydantic>=2.5.0
Requires-Dist: pyjwt>=2.8.0
Requires-Dist: python-dotenv>=1.0.0
Requires-Dist: python-multipart>=0.0.6
Requires-Dist: rich>=13.0.0
Requires-Dist: sqlalchemy[asyncio]>=2.0.0
Requires-Dist: sqlmodel>=0.0.14
Requires-Dist: starlette>=0.35.0
Requires-Dist: typer[all]>=0.9.0
Requires-Dist: uvicorn[standard]>=0.27.0
Provides-Extra: admin
Requires-Dist: jinja2>=3.1.0; extra == 'admin'
Provides-Extra: ai
Provides-Extra: all
Requires-Dist: arq>=0.25.0; extra == 'all'
Requires-Dist: black>=24.0.0; extra == 'all'
Requires-Dist: jinja2>=3.1.0; extra == 'all'
Requires-Dist: mkdocs-material>=9.5.0; extra == 'all'
Requires-Dist: mypy>=1.8.0; extra == 'all'
Requires-Dist: pre-commit>=3.6.0; extra == 'all'
Requires-Dist: pytest-asyncio>=0.23.0; extra == 'all'
Requires-Dist: pytest-cov>=4.1.0; extra == 'all'
Requires-Dist: pytest>=7.4.0; extra == 'all'
Requires-Dist: redis>=5.0.0; extra == 'all'
Requires-Dist: ruff>=0.9.1; extra == 'all'
Provides-Extra: dev
Requires-Dist: black>=24.0.0; extra == 'dev'
Requires-Dist: mkdocs-material>=9.5.0; extra == 'dev'
Requires-Dist: mypy>=1.8.0; extra == 'dev'
Requires-Dist: pre-commit>=3.6.0; extra == 'dev'
Requires-Dist: pytest-asyncio>=0.23.0; extra == 'dev'
Requires-Dist: pytest-cov>=4.1.0; extra == 'dev'
Requires-Dist: pytest>=7.4.0; extra == 'dev'
Requires-Dist: ruff>=0.9.1; extra == 'dev'
Provides-Extra: tasks
Requires-Dist: arq>=0.25.0; extra == 'tasks'
Requires-Dist: redis>=5.0.0; extra == 'tasks'
